MANIFEST.in
README.rst
requirements.txt
setup.py
map4_cli.egg-info/PKG-INFO
map4_cli.egg-info/SOURCES.txt
map4_cli.egg-info/dependency_links.txt
map4_cli.egg-info/entry_points.txt
map4_cli.egg-info/requires.txt
map4_cli.egg-info/top_level.txt
src/__init__.py
src/docker_process.py
src/initializer.py
src/login.py
src/root.py
src/templete/README.md
src/templete/config.json
src/templete/docker-compose.yaml
src/templete/file_storage/files/map4_engine.yaml
src/templete/file_storage/files/min_test.bag
src/templete/file_storage/logs/init.log