Metadata-Version: 1.0
Name: map4-cli
Version: 0.0.12
Summary: Map4 CLI Tool
Home-page: https://github.com/****
Author: Rui Hirano
Author-email: rui.hirano@xxxx.jp
License: MIT
Platform: UNKNOWN
